climpred/__init__.py
climpred/alignment.py
climpred/bias_removal.py
climpred/bootstrap.py
climpred/checks.py
climpred/classes.py
climpred/comparisons.py
climpred/conftest.py
climpred/constants.py
climpred/exceptions.py
climpred/graphics.py
climpred/horizon.py
climpred/logging.py
climpred/metrics.py
climpred/options.py
climpred/prediction.py
climpred/reference.py
climpred/relative_entropy.py
climpred/smoothing.py
climpred/stats.py
climpred/testing.py
climpred/tutorial.py
climpred/utils.py
climpred/preprocessing/__init__.py
climpred/preprocessing/mpi.py
climpred/preprocessing/shared.py
climpred/tests/__init__.py
climpred/tests/test_HindcastEnsemble_class.py
climpred/tests/test_PerfectModelEnsemble_class.py
climpred/tests/test_PredictionEnsemble.py
climpred/tests/test_alignment.py
climpred/tests/test_bias_removal.py
climpred/tests/test_bootstrap.py
climpred/tests/test_checks.py
climpred/tests/test_comparisons.py
climpred/tests/test_compute_dims.py
climpred/tests/test_demo_data.py
climpred/tests/test_effective_p_value.py
climpred/tests/test_graphics.py
climpred/tests/test_hindcast_prediction.py
climpred/tests/test_horizon.py
climpred/tests/test_lead_time_resolutions.py
climpred/tests/test_logging.py
climpred/tests/test_map.py
climpred/tests/test_metrics.py
climpred/tests/test_metrics_perfect.py
climpred/tests/test_options.py
climpred/tests/test_perfect_model_prediction.py
climpred/tests/test_preprocessing.py
climpred/tests/test_probabilistic.py
climpred/tests/test_reference.py
climpred/tests/test_relative_entropy.py
climpred/tests/test_repr.py
climpred/tests/test_smoothing.py
climpred/tests/test_stats.py
climpred/tests/test_uninitialized.py
climpred/tests/test_utils.py
climpred/tests/test_valid_time.py
climpred/tests/test_versioning.py
climpred/versioning/__init__.py
climpred/versioning/print_versions.py
climpred-2.5.0.dist-info/LICENSE.txt
climpred-2.5.0.dist-info/METADATA
climpred-2.5.0.dist-info/WHEEL
climpred-2.5.0.dist-info/top_level.txt
climpred-2.5.0.dist-info/RECORD
