Metadata-Version: 2.1
Name: climpred
Version: 2.5.0
Summary: """Verification of weather and climate forecasts and prediction."""
Author-email: Aaron Spring <aaron.spring@mpimet.mpg.de>, Riley Brady <riley.brady@colorado.edu>
Maintainer-email: Aaron Spring <aaron.spring@mpimet.mpg.de>, Trevor James Smith <smith.trevorj@ouranos.ca>
License: Copyright (c) 2018 The Python Packaging Authority
Project-URL: Homepage, https://climpred.readthedocs.io/en/stable/
Project-URL: Source, https://github.com/pangeo-data/climpred
Project-URL: Changelog, https://climpred.readthedocs.io/en/stable/changelog.html
Project-URL: Issue Tracker, https://github.com/pangeo-data/climpred/issues
Classifier: Development Status :: 5 - Production/Stable
Classifier: Intended Audience :: Education
Classifier: Intended Audience :: Science/Research
Classifier: License :: OSI Approved :: MIT License
Classifier: Natural Language :: English
Classifier: Operating System :: OS Independent
Classifier: Programming Language :: Python :: 3 :: Only
Classifier: Programming Language :: Python :: 3.9
Classifier: Programming Language :: Python :: 3.10
Classifier: Programming Language :: Python :: 3.11
Classifier: Programming Language :: Python :: 3.12
Classifier: Topic :: Scientific/Engineering :: Atmospheric Science
Requires-Python: >=3.9
License-File: LICENSE.txt
Requires-Dist: cf-xarray >=0.6.0
Requires-Dist: cftime >=1.5.0
Requires-Dist: dask >=2021.10.0
Requires-Dist: numpy >=1.25.0
Requires-Dist: packaging
Requires-Dist: pooch >=1.4
Requires-Dist: xarray >=0.19.0
Requires-Dist: xskillscore >=0.0.20
Provides-Extra: accel
Requires-Dist: numba >=0.52 ; extra == 'accel'
Requires-Dist: bottleneck ; extra == 'accel'
Provides-Extra: bias-correction
Requires-Dist: xclim >=0.46 ; extra == 'bias-correction'
Requires-Dist: bias-correction >=0.4 ; extra == 'bias-correction'
Requires-Dist: numpy <2.0.0,>=1.25.0 ; extra == 'bias-correction'
Provides-Extra: complete
Requires-Dist: climpred[accel,bias-correction,io,relative_entropy,test,viz,vwmp] ; extra == 'complete'
Provides-Extra: docs
Requires-Dist: climpred[complete] ; extra == 'docs'
Requires-Dist: myst-nb ; extra == 'docs'
Requires-Dist: sphinx ; extra == 'docs'
Requires-Dist: sphinx-book-theme >=0.3.3 ; extra == 'docs'
Requires-Dist: sphinx-copybutton ; extra == 'docs'
Requires-Dist: sphinxcontrib-bibtex ; extra == 'docs'
Requires-Dist: sphinxcontrib-napoleon ; extra == 'docs'
Provides-Extra: io
Requires-Dist: netcdf4 ; extra == 'io'
Provides-Extra: regridding
Requires-Dist: xesmf ; extra == 'regridding'
Provides-Extra: relative_entropy
Requires-Dist: eofs ; extra == 'relative_entropy'
Provides-Extra: test
Requires-Dist: netcdf4 ; extra == 'test'
Requires-Dist: pre-commit ; extra == 'test'
Requires-Dist: pytest <8.0.0 ; extra == 'test'
Requires-Dist: pytest-cov ; extra == 'test'
Requires-Dist: pytest-lazy-fixture ; extra == 'test'
Requires-Dist: pytest-xdist ; extra == 'test'
Provides-Extra: viz
Requires-Dist: matplotlib ; extra == 'viz'
Requires-Dist: nc-time-axis >=1.4.0 ; extra == 'viz'
Provides-Extra: vwmp
Requires-Dist: xrft ; extra == 'vwmp'
